acme_portal_sdk/__init__.py
acme_portal_sdk/_main.py
acme_portal_sdk/deployment_finder.py
acme_portal_sdk/deployment_promote.py
acme_portal_sdk/flow_deploy.py
acme_portal_sdk/flow_finder.py
acme_portal_sdk/airflow/__init__.py
acme_portal_sdk/airflow/deployment_finder.py
acme_portal_sdk/airflow/deployment_promote.py
acme_portal_sdk/airflow/flow_deploy.py
acme_portal_sdk/airflow/flow_finder.py
acme_portal_sdk/github/__init__.py
acme_portal_sdk/github/github_workflow.py
acme_portal_sdk/prefect/__init__.py
acme_portal_sdk/prefect/deployment_finder.py
acme_portal_sdk/prefect/deployment_promote.py
acme_portal_sdk/prefect/flow_deploy.py
acme_portal_sdk/prefect/flow_finder.py
acme_portal_sdk/prefect/prefect_deploy.py
acme_portal_sdk-1.2.0.dist-info/METADATA
acme_portal_sdk-1.2.0.dist-info/WHEEL
acme_portal_sdk-1.2.0.dist-info/entry_points.txt
acme_portal_sdk-1.2.0.dist-info/top_level.txt
acme_portal_sdk-1.2.0.dist-info/RECORD
