Metadata-Version: 2.4
Name: acme_portal_sdk
Version: 1.2.0
Summary: acme-portal-sdk helps to manage deployments for applications that implement "flows" (Jobs/DAGs/Workflows). It's intended to be used with acme-portal VSCode extension.
Author-email: guner.stan@gmail.com
Project-URL: homepage, https://blackwhitehere.github.io/acme-portal-sdk/
Project-URL: repository, https://github.com/blackwhitehere/acme-portal-sdk
Classifier: Programming Language :: Python :: 3.9
Classifier: Programming Language :: Python :: 3.10
Classifier: Programming Language :: Python :: 3.11
Classifier: Programming Language :: Python :: 3.12
Requires-Python: >=3.9
Requires-Dist: python-dotenv
Provides-Extra: dev
Requires-Dist: pytest; extra == "dev"
Requires-Dist: pytest-cov; extra == "dev"
Requires-Dist: uv; extra == "dev"
Requires-Dist: mkdocs; extra == "dev"
Requires-Dist: mkdocs-material; extra == "dev"
Requires-Dist: mkdocstrings[python]; extra == "dev"
Requires-Dist: jupyterlab; extra == "dev"
Requires-Dist: isort; extra == "dev"
Requires-Dist: ruff; extra == "dev"
Requires-Dist: pre-commit; extra == "dev"
Provides-Extra: prefect
Requires-Dist: prefect; extra == "prefect"
Requires-Dist: acme-config>=0.0.14; extra == "prefect"
Provides-Extra: airflow
Requires-Dist: apache-airflow>=3.0.0; extra == "airflow"
Requires-Dist: requests; extra == "airflow"
